bfh/__init__.py
bfh/common.py
bfh/exceptions.py
bfh/fields.py
bfh/interfaces.py
bfh/transformations.py
bfh/version.py
bfh-0.6.3.dist-info/DESCRIPTION.rst
bfh-0.6.3.dist-info/METADATA
bfh-0.6.3.dist-info/RECORD
bfh-0.6.3.dist-info/WHEEL
bfh-0.6.3.dist-info/metadata.json
bfh-0.6.3.dist-info/top_level.txt
