Metadata-Version: 1.1
Name: bfh
Version: 0.6.3
Summary: Smacks schemas into other schemas
Home-page: https://github.com/percolate/bfh
Author: Evan Bender
Author-email: evan.bender@percolate.com
License: UNKNOWN
Platform: UNKNOWN
Classifier: Development Status :: 4 - Beta
Classifier: License :: OSI Approved :: Mozilla Public License 2.0 (MPL 2.0)
Classifier: Programming Language :: Python :: 2.7
